pysbml/__init__.py
pysbml/py.typed
pysbml/codegen/__init__.py
pysbml/parse/__init__.py
pysbml/parse/data.py
pysbml/parse/l1.py
pysbml/parse/l2.py
pysbml/parse/l3.py
pysbml/parse/mathml.py
pysbml/parse/name_conversion.py
pysbml/parse/units.py
pysbml/transform/__init__.py
pysbml/transform/data.py
pysbml/transform/mathml2sympy.py
pysbml/transform/units.py
pysbml-0.3.0.dist-info/METADATA
pysbml-0.3.0.dist-info/WHEEL
pysbml-0.3.0.dist-info/licenses/LICENSE
pysbml-0.3.0.dist-info/RECORD
