Metadata-Version: 2.4
Name: pysbml
Version: 0.3.0
Summary: Add your description here
Author-email: Marvin van Aalst <marvin.vanaalst@gmail.com>
Maintainer-email: Marvin van Aalst <marvin.vanaalst@gmail.com>
License-Expression: MIT
License-File: LICENSE
Requires-Python: >=3.12
Requires-Dist: python-libsbml>=5.20.4
Requires-Dist: sympy>=1.14.0
